[{"article": {"date_publication": "2018-01-17", "name_newspaper": "20 Minutes", "surname_author": ["Elisa Frisullo"]}, "position_word": [{"word": "Lancer", "lemma": "Lancer", "pos_tag": "VERB", "type_entity": "LOC", "position": 1, "title": false}, {"word": "diaporamaLyon", "lemma": "diaporamaLyon", "pos_tag": "NOUN", "type_entity": "", "position": 3, "title": false}, {"word": "16janvier2018", "lemma": "16janvier2018", "pos_tag": "NOUN", "type_entity": "", "position": 5, "title": false}, {"word": "Des", "lemma": "Des", "pos_tag": "DET", "type_entity": "", "position": 7, "title": true}, {"word": "momies", "lemma": "momie", "pos_tag": "NOUN", "type_entity": "", "position": 8, "title": true}, {"word": "centre", "lemma": "centrer", "pos_tag": "NOUN", "type_entity": "", "position": 10, "title": false}, {"word": "conservation", "lemma": "conservation", "pos_tag": "NOUN", "type_entity": "", "position": 12, "title": false}, {"word": "musee", "lemma": "musee", "pos_tag": "NOUN", "type_entity": "", "position": 14, "title": true}, {"word": "Confluences", "lemma": "Confluences", "pos_tag": "NOUN", "type_entity": "LOC", "position": 16, "title": true}, {"word": "actuellement", "lemma": "actuellement", "pos_tag": "ADV", "type_entity": "", "position": 18, "title": false}, {"word": "etudiees", "lemma": "etudiees", "pos_tag": "ADJ", "type_entity": "", "position": 19, "title": true}, {"word": "grace", "lemma": "grace", "pos_tag": "NOUN", "type_entity": "", "position": 20, "title": true}, {"word": "imagerie", "lemma": "imagerie", "pos_tag": "NOUN", "type_entity": "", "position": 23, "title": false}, {"word": "medicale", "lemma": "medicale", "pos_tag": "ADJ", "type_entity": "", "position": 24, "title": true}, {"word": "cadre", "lemma": "cadrer", "pos_tag": "NOUN", "type_entity": "", "position": 27, "title": false}, {"word": "projet", "lemma": "projet", "pos_tag": "NOUN", "type_entity": "", "position": 30, "title": false}, {"word": "pilote", "lemma": "piloter", "pos_tag": "VERB", "type_entity": "", "position": 31, "title": false}, {"word": "universite", "lemma": "universite", "pos_tag": "NOUN", "type_entity": "", "position": 34, "title": false}, {"word": "Montpelllier", "lemma": "Montpelllier", "pos_tag": "PROPN", "type_entity": "PER", "position": 36, "title": false}, {"word": "E.", "lemma": "E.", "pos_tag": "NOUN", "type_entity": "", "position": 38, "title": false}, {"word": "Frisullo", "lemma": "Frisullo", "pos_tag": "PROPN", "type_entity": "LOC", "position": 39, "title": false}, {"word": "20", "lemma": "20", "pos_tag": "NUM", "type_entity": "", "position": 40, "title": false}, {"word": "MinutesElles", "lemma": "MinutesElles", "pos_tag": "NOUN", "type_entity": "LOC", "position": 41, "title": false}, {"word": "tronent", "lemma": "tronent", "pos_tag": "VERB", "type_entity": "", "position": 42, "title": false}, {"word": "collections", "lemma": "collection", "pos_tag": "NOUN", "type_entity": "", "position": 45, "title": false}, {"word": "musees", "lemma": "musees", "pos_tag": "NOUN", "type_entity": "", "position": 47, "title": false}, {"word": "lyonnais", "lemma": "lyonnais", "pos_tag": "ADJ", "type_entity": "", "position": 48, "title": false}, {"word": "siecle", "lemma": "siecle", "pos_tag": "NOUN", "type_entity": "", "position": 53, "title": false}, {"word": "jusqu", "lemma": "jusqu", "pos_tag": "VERB", "type_entity": "", "position": 56, "title": false}, {"word": "jamais", "lemma": "jamais", "pos_tag": "ADV", "type_entity": "", "position": 61, "title": false}, {"word": "livre", "lemma": "livrer", "pos_tag": "VERB", "type_entity": "", "position": 62, "title": false}, {"word": "secret", "lemma": "secret", "pos_tag": "NOUN", "type_entity": "", "position": 64, "title": false}, {"word": "semaines", "lemma": "semaine", "pos_tag": "NOUN", "type_entity": "", "position": 68, "title": false}, {"word": "27", "lemma": "27", "pos_tag": "NUM", "type_entity": "", "position": 69, "title": false}, {"word": "momies", "lemma": "momie", "pos_tag": "NOUN", "type_entity": "", "position": 70, "title": true}, {"word": "41", "lemma": "41", "pos_tag": "NUM", "type_entity": "", "position": 72, "title": false}, {"word": "tetes", "lemma": "tetes", "pos_tag": "NOUN", "type_entity": "", "position": 73, "title": false}, {"word": "momies", "lemma": "momie", "pos_tag": "NOUN", "type_entity": "", "position": 75, "title": true}, {"word": "etudiees", "lemma": "etudiees", "pos_tag": "VERB", "type_entity": "", "position": 77, "title": true}, {"word": "Lyon", "lemma": "Lyon", "pos_tag": "ADP", "type_entity": "LOC", "position": 79, "title": false}, {"word": "centre", "lemma": "centrer", "pos_tag": "NOUN", "type_entity": "", "position": 82, "title": false}, {"word": "conservation", "lemma": "conservation", "pos_tag": "NOUN", "type_entity": "", "position": 84, "title": false}, {"word": "etude", "lemma": "etude", "pos_tag": "NOUN", "type_entity": "", "position": 87, "title": false}, {"word": "collections", "lemma": "collection", "pos_tag": "NOUN", "type_entity": "", "position": 89, "title": false}, {"word": "musee", "lemma": "musee", "pos_tag": "NOUN", "type_entity": "", "position": 91, "title": true}, {"word": "Confluences", "lemma": "Confluences", "pos_tag": "NOUN", "type_entity": "LOC", "position": 93, "title": true}, {"word": "cadre", "lemma": "cadrer", "pos_tag": "NOUN", "type_entity": "", "position": 96, "title": false}, {"word": "projet", "lemma": "projet", "pos_tag": "NOUN", "type_entity": "", "position": 99, "title": false}, {"word": "pilote", "lemma": "piloter", "pos_tag": "VERB", "type_entity": "", "position": 100, "title": false}, {"word": "Universite_de_Montpellier", "lemma": "Universite_de_Montpellier", "pos_tag": "NOUN", "type_entity": "PER", "position": 103, "title": false}, {"word": "tresors", "lemma": "tresors", "pos_tag": "NUM", "type_entity": "", "position": 106, "title": false}, {"word": "ramenes", "lemma": "ramenes", "pos_tag": "NOUN", "type_entity": "", "position": 107, "title": false}, {"word": "Egypte", "lemma": "Egypte", "pos_tag": "PROPN", "type_entity": "LOC", "position": 109, "title": false}, {"word": "fin", "lemma": "fin", "pos_tag": "NOUN", "type_entity": "", "position": 112, "title": false}, {"word": "XIXe_siecle", "lemma": "XIXe_siecle", "pos_tag": "NOUN", "type_entity": "MISC", "position": 114, "title": false}, {"word": "debut", "lemma": "debut", "pos_tag": "VERB", "type_entity": "", "position": 117, "title": false}, {"word": "XXe_siecle", "lemma": "XXe_siecle", "pos_tag": "NOUN", "type_entity": "MISC", "position": 119, "title": false}, {"word": "CharlesLouis_Lortet", "lemma": "CharlesLouis_Lortet", "pos_tag": "PROPN", "type_entity": "PER", "position": 121, "title": false}, {"word": "doyen", "lemma": "doyen", "pos_tag": "NOUN", "type_entity": "", "position": 122, "title": false}, {"word": "faculte", "lemma": "faculte", "pos_tag": "NOUN", "type_entity": "", "position": 125, "title": false}, {"word": "medecine_de", "lemma": "medecine_de", "pos_tag": "NOUN", "type_entity": "LOC", "position": 127, "title": false}, {"word": "Lyon", "lemma": "Lyon", "pos_tag": "PROPN", "type_entity": "LOC", "position": 128, "title": false}, {"word": "directeur", "lemma": "directeur", "pos_tag": "NOUN", "type_entity": "", "position": 130, "title": false}, {"word": "ancien", "lemma": "ancien", "pos_tag": "ADJ", "type_entity": "", "position": 133, "title": false}, {"word": "museum", "lemma": "museum", "pos_tag": "NOUN", "type_entity": "", "position": 134, "title": false}, {"word": "histoire", "lemma": "histoire", "pos_tag": "NOUN", "type_entity": "", "position": 136, "title": false}, {"word": "naturelle", "lemma": "naturel", "pos_tag": "ADJ", "type_entity": "", "position": 137, "title": false}, {"word": "Lyon", "lemma": "Lyon", "pos_tag": "PROPN", "type_entity": "LOC", "position": 139, "title": false}, {"word": "jamais", "lemma": "jamais", "pos_tag": "ADV", "type_entity": "", "position": 142, "title": false}, {"word": "ete", "lemma": "ete", "pos_tag": "DET", "type_entity": "", "position": 143, "title": false}, {"word": "explores", "lemma": "explorer", "pos_tag": "ADJ", "type_entity": "", "position": 144, "title": false}, {"word": "jusqu", "lemma": "jusqu", "pos_tag": "VERB", "type_entity": "", "position": 145, "title": false}, {"word": "present", "lemma": "present", "pos_tag": "VERB", "type_entity": "", "position": 147, "title": false}, {"word": "Pour", "lemma": "Pour", "pos_tag": "ADP", "type_entity": "", "position": 149, "title": true}, {"word": "faire", "lemma": "faire", "pos_tag": "VERB", "type_entity": "", "position": 150, "title": false}, {"word": "momies", "lemma": "momie", "pos_tag": "NOUN", "type_entity": "", "position": 153, "title": true}, {"word": "risquer", "lemma": "risquer", "pos_tag": "NOUN", "type_entity": "", "position": 155, "title": false}, {"word": "deteriorer", "lemma": "deteriorer", "pos_tag": "VERB", "type_entity": "", "position": 158, "title": false}, {"word": "chercheurs", "lemma": "chercheur", "pos_tag": "ADJ", "type_entity": "", "position": 160, "title": false}, {"word": "charges", "lemma": "charger", "pos_tag": "NOUN", "type_entity": "", "position": 161, "title": false}, {"word": "projet", "lemma": "projet", "pos_tag": "NOUN", "type_entity": "", "position": 163, "title": false}, {"word": "utilisent", "lemma": "utiliser", "pos_tag": "ADV", "type_entity": "", "position": 164, "title": false}, {"word": "mobile", "lemma": "mobile", "pos_tag": "NOUN", "type_entity": "", "position": 166, "title": false}, {"word": "radiologie", "lemma": "radiologie", "pos_tag": "NOUN", "type_entity": "", "position": 168, "title": false}, {"word": "medicale", "lemma": "medicale", "pos_tag": "ADJ", "type_entity": "", "position": 169, "title": true}, {"word": "habituellement", "lemma": "habituellement", "pos_tag": "ADV", "type_entity": "", "position": 170, "title": false}, {"word": "utilise", "lemma": "utiliser", "pos_tag": "VERB", "type_entity": "", "position": 171, "title": false}, {"word": "hopitaux", "lemma": "hopitaux", "pos_tag": "NOUN", "type_entity": "", "position": 174, "title": false}, {"word": "appareil", "lemma": "appareil", "pos_tag": "NOUN", "type_entity": "", "position": 177, "title": false}, {"word": "mis", "lemma": "mettre", "pos_tag": "VERB", "type_entity": "", "position": 179, "title": false}, {"word": "disposition", "lemma": "disposition", "pos_tag": "VERB", "type_entity": "", "position": 181, "title": false}, {"word": "Samsung", "lemma": "Samsung", "pos_tag": "PROPN", "type_entity": "ORG", "position": 183, "title": false}, {"word": "cadre", "lemma": "cadrer", "pos_tag": "NOUN", "type_entity": "", "position": 186, "title": false}, {"word": "partenariat", "lemma": "partenariat", "pos_tag": "NOUN", "type_entity": "", "position": 189, "title": false}, {"word": "inedit", "lemma": "inedit", "pos_tag": "VERB", "type_entity": "", "position": 190, "title": false}, {"word": "lire", "lemma": "lire", "pos_tag": "VERB", "type_entity": "", "position": 193, "title": false}, {"word": "VIDEO", "lemma": "VIDEO", "pos_tag": "ADJ", "type_entity": "MISC", "position": 195, "title": false}, {"word": "Des", "lemma": "Des", "pos_tag": "DET", "type_entity": "", "position": 197, "title": true}, {"word": "archeologues", "lemma": "archeologues", "pos_tag": "ADJ", "type_entity": "", "position": 198, "title": false}, {"word": "egyptiens", "lemma": "egyptiens", "pos_tag": "ADJ", "type_entity": "", "position": 199, "title": false}, {"word": "decouvrent", "lemma": "decouvrent", "pos_tag": "VERB", "type_entity": "", "position": 200, "title": false}, {"word": "momie", "lemma": "momi", "pos_tag": "NOUN", "type_entity": "", "position": 202, "title": false}, {"word": "Louxor_L", "lemma": "Louxor_L", "pos_tag": "ADV", "type_entity": "ORG", "position": 204, "title": false}, {"word": "interet", "lemma": "interet", "pos_tag": "NOUN", "type_entity": "", "position": 205, "title": false}, {"word": "majeur", "lemma": "majeur", "pos_tag": "ADJ", "type_entity": "", "position": 206, "title": false}, {"word": "imagerie", "lemma": "imagerie", "pos_tag": "NOUN", "type_entity": "", "position": 209, "title": false}, {"word": "medicale", "lemma": "medicale", "pos_tag": "ADJ", "type_entity": "", "position": 210, "title": true}, {"word": "methode", "lemma": "methode", "pos_tag": "ADJ", "type_entity": "", "position": 217, "title": false}, {"word": "invasive", "lemma": "invasif", "pos_tag": "ADJ", "type_entity": "", "position": 219, "title": false}, {"word": "va", "lemma": "aller", "pos_tag": "VERB", "type_entity": "", "position": 221, "title": false}, {"word": "permettre", "lemma": "permettre", "pos_tag": "VERB", "type_entity": "", "position": 222, "title": false}, {"word": "connaitre", "lemma": "connaitre", "pos_tag": "VERB", "type_entity": "", "position": 224, "title": false}, {"word": "interieur", "lemma": "interieur", "pos_tag": "NOUN", "type_entity": "", "position": 226, "title": false}, {"word": "momie", "lemma": "momi", "pos_tag": "NOUN", "type_entity": "", "position": 229, "title": false}, {"word": "abimer", "lemma": "abimer", "pos_tag": "VERB", "type_entity": "", "position": 232, "title": false}, {"word": "deplacer", "lemma": "deplacer", "pos_tag": "VERB", "type_entity": "", "position": 238, "title": false}, {"word": "explique", "lemma": "expliquer", "pos_tag": "VERB", "type_entity": "", "position": 239, "title": false}, {"word": "Annie_Perraud", "lemma": "Annie_Perraud", "pos_tag": "PROPN", "type_entity": "PER", "position": 240, "title": false}, {"word": "docteur", "lemma": "docteur", "pos_tag": "NOUN", "type_entity": "", "position": 241, "title": false}, {"word": "egyptologie", "lemma": "egyptologie", "pos_tag": "NOUN", "type_entity": "", "position": 243, "title": false}, {"word": "specialisee", "lemma": "specialisee", "pos_tag": "ADJ", "type_entity": "", "position": 244, "title": false}, {"word": "momie", "lemma": "momi", "pos_tag": "NOUN", "type_entity": "", "position": 247, "title": false}, {"word": "humaine", "lemma": "humain", "pos_tag": "ADJ", "type_entity": "", "position": 248, "title": false}, {"word": "universite", "lemma": "universite", "pos_tag": "NOUN", "type_entity": "", "position": 251, "title": false}, {"word": "Montpellier", "lemma": "Montpellier", "pos_tag": "PROPN", "type_entity": "LOC", "position": 253, "title": false}, {"word": "Une", "lemma": "Une", "pos_tag": "DET", "type_entity": "", "position": 255, "title": false}, {"word": "pratique", "lemma": "pratiquer", "pos_tag": "NOUN", "type_entity": "", "position": 256, "title": false}, {"word": "respectueuse", "lemma": "respectueux", "pos_tag": "ADJ", "type_entity": "", "position": 257, "title": false}, {"word": "anime", "lemma": "animer", "pos_tag": "VERB", "type_entity": "", "position": 263, "title": false}, {"word": "scientifiques", "lemma": "scientifique", "pos_tag": "NOUN", "type_entity": "", "position": 265, "title": false}, {"word": "passe", "lemma": "passer", "pos_tag": "NOUN", "type_entity": "", "position": 268, "title": false}, {"word": "Beaucoup", "lemma": "Beaucoup", "pos_tag": "PRON", "type_entity": "", "position": 270, "title": false}, {"word": "momies", "lemma": "momie", "pos_tag": "NOUN", "type_entity": "", "position": 272, "title": true}, {"word": "royales", "lemma": "royale", "pos_tag": "ADJ", "type_entity": "", "position": 273, "title": false}, {"word": "ete", "lemma": "ete", "pos_tag": "AUX", "type_entity": "", "position": 275, "title": false}, {"word": "debandelettees", "lemma": "debandelettees", "pos_tag": "ADJ", "type_entity": "", "position": 276, "title": false}, {"word": "cas", "lemma": "cas", "pos_tag": "NOUN", "type_entity": "", "position": 281, "title": false}, {"word": "Ramses_II", "lemma": "Ramses_II", "pos_tag": "VERB", "type_entity": "PER", "position": 283, "title": false}, {"word": "retire", "lemma": "retirer", "pos_tag": "VERB", "type_entity": "", "position": 287, "title": false}, {"word": "bandelettes", "lemma": "bandelette", "pos_tag": "NOUN", "type_entity": "", "position": 289, "title": false}, {"word": "entourant", "lemma": "entourer", "pos_tag": "VERB", "type_entity": "", "position": 290, "title": false}, {"word": "corps", "lemma": "corps", "pos_tag": "NOUN", "type_entity": "", "position": 292, "title": false}, {"word": "matinee", "lemma": "matinee", "pos_tag": "NOUN", "type_entity": "", "position": 295, "title": false}, {"word": "rappelle", "lemma": "rappeler", "pos_tag": "VERB", "type_entity": "", "position": 296, "title": false}, {"word": "Dr", "lemma": "Dr", "pos_tag": "NOUN", "type_entity": "MISC", "position": 298, "title": false}, {"word": "Roger_Lichtenberg", "lemma": "Roger_Lichtenberg", "pos_tag": "ADJ", "type_entity": "PER", "position": 299, "title": false}, {"word": "radiologue", "lemma": "radiologue", "pos_tag": "NOUN", "type_entity": "", "position": 301, "title": false}, {"word": "implique", "lemma": "impliquer", "pos_tag": "ADJ", "type_entity": "", "position": 302, "title": false}, {"word": "projet", "lemma": "projet", "pos_tag": "NOUN", "type_entity": "", "position": 305, "title": false}, {"word": "<", "lemma": "<", "pos_tag": "ADP", "type_entity": "", "position": 307, "title": false}, {"word": "<", "lemma": "<", "pos_tag": "PRON", "type_entity": "", "position": 308, "title": false}, {"word": "fallu", "lemma": "falloir", "pos_tag": "VERB", "type_entity": "", "position": 311, "title": false}, {"word": "attendre", "lemma": "attendre", "pos_tag": "VERB", "type_entity": "", "position": 312, "title": false}, {"word": "annees", "lemma": "annees", "pos_tag": "ADP", "type_entity": "", "position": 314, "title": false}, {"word": "1980", "lemma": "1980", "pos_tag": "NUM", "type_entity": "", "position": 315, "title": false}, {"word": "vraie", "lemma": "vrai", "pos_tag": "NOUN", "type_entity": "", "position": 322, "title": false}, {"word": "prise", "lemma": "priser", "pos_tag": "NOUN", "type_entity": "", "position": 323, "title": false}, {"word": "conscience", "lemma": "conscience", "pos_tag": "NOUN", "type_entity": "", "position": 325, "title": false}, {"word": "rende", "lemma": "rendre", "pos_tag": "VERB", "type_entity": "", "position": 331, "title": false}, {"word": "compte", "lemma": "compter", "pos_tag": "VERB", "type_entity": "", "position": 332, "title": false}, {"word": "agissant", "lemma": "agir", "pos_tag": "VERB", "type_entity": "", "position": 335, "title": false}, {"word": "sorte", "lemma": "sortir", "pos_tag": "NOUN", "type_entity": "", "position": 338, "title": false}, {"word": "detruisait", "lemma": "detruisait", "pos_tag": "VERB", "type_entity": "", "position": 340, "title": false}, {"word": "momies", "lemma": "momie", "pos_tag": "NOUN", "type_entity": "", "position": 342, "title": true}, {"word": "irremediablement", "lemma": "irremediablement", "pos_tag": "VERB", "type_entity": "", "position": 343, "title": false}, {"word": ">", "lemma": ">", "pos_tag": "SCONJ", "type_entity": "", "position": 344, "title": false}, {"word": ">", "lemma": ">", "pos_tag": "PRON", "type_entity": "", "position": 345, "title": false}, {"word": ",", "lemma": ",", "pos_tag": "PUNCT", "type_entity": "", "position": 346, "title": false}, {"word": "ajoute", "lemma": "ajouter", "pos_tag": "VERB", "type_entity": "", "position": 347, "title": false}, {"word": "egyptologue", "lemma": "egyptologue", "pos_tag": "NOUN", "type_entity": "", "position": 349, "title": false}, {"word": ",", "lemma": ",", "pos_tag": "PUNCT", "type_entity": "", "position": 350, "title": false}, {"word": "soucieuse", "lemma": "soucieux", "pos_tag": "ADJ", "type_entity": "", "position": 351, "title": false}, {"word": "desormais", "lemma": "desormais", "pos_tag": "NOUN", "type_entity": "", "position": 352, "title": false}, {"word": "apprendre", "lemma": "avoir", "pos_tag": "VERB", "type_entity": "", "position": 355, "title": false}, {"word": "cadavres", "lemma": "cadavre", "pos_tag": "NOUN", "type_entity": "", "position": 359, "title": false}, {"word": "embaumes", "lemma": "embaumer", "pos_tag": "ADJ", "type_entity": "", "position": 360, "title": false}, {"word": "abrites", "lemma": "abriter", "pos_tag": "ADJ", "type_entity": "", "position": 361, "title": false}, {"word": "Lyon", "lemma": "Lyon", "pos_tag": "PROPN", "type_entity": "LOC", "position": 363, "title": false}, {"word": "Cette", "lemma": "Cette", "pos_tag": "DET", "type_entity": "", "position": 365, "title": false}, {"word": "etude", "lemma": "etude", "pos_tag": "NOUN", "type_entity": "", "position": 366, "title": false}, {"word": "va", "lemma": "aller", "pos_tag": "VERB", "type_entity": "", "position": 367, "title": false}, {"word": "permettre", "lemma": "permettre", "pos_tag": "VERB", "type_entity": "", "position": 370, "title": false}, {"word": ",", "lemma": ",", "pos_tag": "PUNCT", "type_entity": "", "position": 371, "title": false}, {"word": "grace", "lemma": "grace", "pos_tag": "NOUN", "type_entity": "", "position": 372, "title": true}, {"word": "images", "lemma": "image", "pos_tag": "NOUN", "type_entity": "", "position": 374, "title": false}, {"word": "grande", "lemma": "grand", "pos_tag": "ADJ", "type_entity": "", "position": 376, "title": false}, {"word": "precision", "lemma": "precision", "pos_tag": "NOUN", "type_entity": "", "position": 377, "title": false}, {"word": "imagerie", "lemma": "imagerie", "pos_tag": "NOUN", "type_entity": "", "position": 380, "title": false}, {"word": ",", "lemma": ",", "pos_tag": "PUNCT", "type_entity": "", "position": 381, "title": false}, {"word": "enrichir", "lemma": "enrichir", "pos_tag": "VERB", "type_entity": "", "position": 383, "title": false}, {"word": "connaissances", "lemma": "connaissance", "pos_tag": "NOUN", "type_entity": "", "position": 385, "title": false}, {"word": "procedes", "lemma": "procedes", "pos_tag": "NOUN", "type_entity": "", "position": 388, "title": false}, {"word": "momification", "lemma": "momification", "pos_tag": "NOUN", "type_entity": "", "position": 390, "title": false}, {"word": "<", "lemma": "<", "pos_tag": "ADP", "type_entity": "", "position": 392, "title": false}, {"word": "<", "lemma": "<", "pos_tag": "VERB", "type_entity": "", "position": 393, "title": false}, {"word": "Cela", "lemma": "Cela", "pos_tag": "PRON", "type_entity": "", "position": 394, "title": false}, {"word": "va", "lemma": "aller", "pos_tag": "VERB", "type_entity": "", "position": 395, "title": false}, {"word": "permettre", "lemma": "permettre", "pos_tag": "VERB", "type_entity": "", "position": 397, "title": false}, {"word": "egalement", "lemma": "egalement", "pos_tag": "ADV", "type_entity": "", "position": 398, "title": false}, {"word": "savoir", "lemma": "savoir", "pos_tag": "VERB", "type_entity": "", "position": 401, "title": false}, {"word": "etat", "lemma": "etat", "pos_tag": "NOUN", "type_entity": "", "position": 405, "title": false}, {"word": "sante", "lemma": "sante", "pos_tag": "NOUN", "type_entity": "", "position": 407, "title": false}, {"word": "defunts", "lemma": "defunts", "pos_tag": "NOUN", "type_entity": "", "position": 410, "title": false}, {"word": "poser", "lemma": "poser", "pos_tag": "VERB", "type_entity": "", "position": 413, "title": false}, {"word": "diagnostic", "lemma": "diagnostic", "pos_tag": "NOUN", "type_entity": "", "position": 415, "title": false}, {"word": "anthropologique", "lemma": "anthropologique", "pos_tag": "ADJ", "type_entity": "", "position": 416, "title": false}, {"word": ",", "lemma": ",", "pos_tag": "PUNCT", "type_entity": "", "position": 417, "title": false}, {"word": "est-a-dire", "lemma": "est-a-dire", "pos_tag": "NOUN", "type_entity": "", "position": 419, "title": false}, {"word": "connaitre", "lemma": "connaitre", "pos_tag": "VERB", "type_entity": "", "position": 421, "title": false}, {"word": "sexe", "lemma": "sexe", "pos_tag": "NOUN", "type_entity": "", "position": 423, "title": false}, {"word": ",", "lemma": ",", "pos_tag": "PUNCT", "type_entity": "", "position": 424, "title": false}, {"word": "determiner", "lemma": "determiner", "pos_tag": "VERB", "type_entity": "", "position": 426, "title": false}, {"word": "tranche", "lemma": "trancher", "pos_tag": "NOUN", "type_entity": "", "position": 428, "title": false}, {"word": "age", "lemma": "age", "pos_tag": "NOUN", "type_entity": "", "position": 430, "title": false}, {"word": ">", "lemma": ">", "pos_tag": "PRON", "type_entity": "", "position": 431, "title": false}, {"word": ">", "lemma": ">", "pos_tag": "PRON", "type_entity": "", "position": 432, "title": false}, {"word": ",", "lemma": ",", "pos_tag": "PUNCT", "type_entity": "", "position": 433, "title": false}, {"word": "detaille", "lemma": "detaille", "pos_tag": "NOUN", "type_entity": "", "position": 434, "title": false}, {"word": "Annie_Perraud", "lemma": "Annie_Perraud", "pos_tag": "PROPN", "type_entity": "PER", "position": 435, "title": false}, {"word": "recherches", "lemma": "rechercher", "pos_tag": "NOUN", "type_entity": "", "position": 438, "title": false}, {"word": "devraient", "lemma": "devoir", "pos_tag": "VERB", "type_entity": "", "position": 439, "title": false}, {"word": "egalement", "lemma": "egalement", "pos_tag": "ADV", "type_entity": "", "position": 440, "title": false}, {"word": "offrir", "lemma": "offrir", "pos_tag": "VERB", "type_entity": "", "position": 441, "title": false}, {"word": ",", "lemma": ",", "pos_tag": "PUNCT", "type_entity": "", "position": 442, "title": false}, {"word": "ici", "lemma": "ici", "pos_tag": "ADV", "type_entity": "", "position": 444, "title": false}, {"word": "ans", "lemma": "an", "pos_tag": "NOUN", "type_entity": "", "position": 447, "title": false}, {"word": ",", "lemma": ",", "pos_tag": "PUNCT", "type_entity": "", "position": 448, "title": false}, {"word": "datation", "lemma": "datation", "pos_tag": "NOUN", "type_entity": "", "position": 450, "title": false}, {"word": "precise", "lemma": "precise", "pos_tag": "NOUN", "type_entity": "", "position": 452, "title": false}, {"word": "momies", "lemma": "momie", "pos_tag": "NOUN", "type_entity": "", "position": 455, "title": true}, {"word": ",", "lemma": ",", "pos_tag": "PUNCT", "type_entity": "", "position": 456, "title": false}, {"word": "remontent", "lemma": "remonter", "pos_tag": "VERB", "type_entity": "", "position": 458, "title": false}, {"word": "periode", "lemma": "periode", "pos_tag": "NOUN", "type_entity": "", "position": 461, "title": false}, {"word": "ptolemaique", "lemma": "ptolemaique", "pos_tag": "ADJ", "type_entity": "", "position": 462, "title": false}, {"word": ",", "lemma": ",", "pos_tag": "PUNCT", "type_entity": "", "position": 463, "title": false}, {"word": "-300", "lemma": "-300", "pos_tag": "ADV", "type_entity": "", "position": 465, "title": false}, {"word": "ere", "lemma": "ere", "pos_tag": "NOUN", "type_entity": "", "position": 468, "title": false}, {"word": "<", "lemma": "<", "pos_tag": "ADP", "type_entity": "", "position": 470, "title": false}, {"word": "<", "lemma": "<", "pos_tag": "VERB", "type_entity": "", "position": 471, "title": false}, {"word": "Quand", "lemma": "Quand", "pos_tag": "SCONJ", "type_entity": "", "position": 472, "title": false}, {"word": "radiographie", "lemma": "radiographier", "pos_tag": "VERB", "type_entity": "", "position": 474, "title": false}, {"word": "momie", "lemma": "momi", "pos_tag": "NOUN", "type_entity": "", "position": 476, "title": false}, {"word": ",", "lemma": ",", "pos_tag": "PUNCT", "type_entity": "", "position": 477, "title": false}, {"word": "attends", "lemma": "attendre", "pos_tag": "ADJ", "type_entity": "", "position": 480, "title": false}, {"word": "Je", "lemma": "Je", "pos_tag": "PRON", "type_entity": "", "position": 484, "title": false}, {"word": "medecin", "lemma": "medecin", "pos_tag": "NOUN", "type_entity": "", "position": 488, "title": false}, {"word": "legiste", "lemma": "legiste", "pos_tag": "ADJ", "type_entity": "", "position": 489, "title": false}, {"word": "essaye", "lemma": "essayer", "pos_tag": "VERB", "type_entity": "", "position": 492, "title": false}, {"word": "faire", "lemma": "faire", "pos_tag": "VERB", "type_entity": "", "position": 494, "title": false}, {"word": "diagnostic", "lemma": "diagnostic", "pos_tag": "NOUN", "type_entity": "", "position": 496, "title": false}, {"word": "post-mortem", "lemma": "post-mortem", "pos_tag": "ADJ", "type_entity": "", "position": 497, "title": false}, {"word": ">", "lemma": ">", "pos_tag": "PRON", "type_entity": "", "position": 498, "title": false}, {"word": ">", "lemma": ">", "pos_tag": "PRON", "type_entity": "", "position": 499, "title": false}, {"word": ",", "lemma": ",", "pos_tag": "PUNCT", "type_entity": "", "position": 500, "title": false}, {"word": "ajoute", "lemma": "ajouter", "pos_tag": "VERB", "type_entity": "", "position": 501, "title": false}, {"word": ",", "lemma": ",", "pos_tag": "PUNCT", "type_entity": "", "position": 502, "title": false}, {"word": "passionne", "lemma": "passionner", "pos_tag": "VERB", "type_entity": "", "position": 503, "title": false}, {"word": ",", "lemma": ",", "pos_tag": "PUNCT", "type_entity": "", "position": 504, "title": false}, {"word": "Dr_Lichtenberg", "lemma": "Dr_Lichtenberg", "pos_tag": "NOUN", "type_entity": "LOC", "position": 506, "title": false}, {"word": ",", "lemma": ",", "pos_tag": "PUNCT", "type_entity": "", "position": 507, "title": false}, {"word": "etudie", "lemma": "etudie", "pos_tag": "NOUN", "type_entity": "", "position": 510, "title": false}, {"word": "350", "lemma": "350", "pos_tag": "NUM", "type_entity": "", "position": 513, "title": false}, {"word": "momies", "lemma": "momie", "pos_tag": "NOUN", "type_entity": "", "position": 514, "title": true}, {"word": "cours", "lemma": "courir", "pos_tag": "NOUN", "type_entity": "", "position": 516, "title": false}, {"word": "carriere", "lemma": "carriere", "pos_tag": "NOUN", "type_entity": "", "position": 519, "title": false}, {"word": "<", "lemma": "<", "pos_tag": "ADP", "type_entity": "", "position": 521, "title": false}, {"word": "<", "lemma": "<", "pos_tag": "VERB", "type_entity": "", "position": 522, "title": false}, {"word": "Quand", "lemma": "Quand", "pos_tag": "SCONJ", "type_entity": "", "position": 523, "title": false}, {"word": "desert", "lemma": "desert", "pos_tag": "NOUN", "type_entity": "", "position": 528, "title": false}, {"word": "dois", "lemma": "devoir", "pos_tag": "AUX", "type_entity": "", "position": 532, "title": false}, {"word": "radiographier", "lemma": "radiographier", "pos_tag": "VERB", "type_entity": "", "position": 533, "title": false}, {"word": "momie", "lemma": "momi", "pos_tag": "NOUN", "type_entity": "", "position": 535, "title": false}, {"word": ",", "lemma": ",", "pos_tag": "PUNCT", "type_entity": "", "position": 536, "title": false}, {"word": "dois", "lemma": "devoir", "pos_tag": "AUX", "type_entity": "", "position": 538, "title": false}, {"word": "faire", "lemma": "faire", "pos_tag": "VERB", "type_entity": "", "position": 539, "title": false}, {"word": "radio", "lemma": "radio", "pos_tag": "NOUN", "type_entity": "", "position": 541, "title": false}, {"word": ",", "lemma": ",", "pos_tag": "PUNCT", "type_entity": "", "position": 542, "title": false}, {"word": "aller", "lemma": "aller", "pos_tag": "VERB", "type_entity": "", "position": 543, "title": false}, {"word": "labo", "lemma": "labo", "pos_tag": "NOUN", "type_entity": "", "position": 546, "title": false}, {"word": "faut", "lemma": "falloir", "pos_tag": "VERB", "type_entity": "", "position": 549, "title": false}, {"word": "temps", "lemma": "temps", "pos_tag": "NOUN", "type_entity": "", "position": 551, "title": false}, {"word": "resultat", "lemma": "resultat", "pos_tag": "NOUN", "type_entity": "", "position": 557, "title": false}, {"word": ",", "lemma": ",", "pos_tag": "PUNCT", "type_entity": "", "position": 560, "title": false}, {"word": "grace", "lemma": "grace", "pos_tag": "NOUN", "type_entity": "", "position": 561, "title": true}, {"word": "imagerie", "lemma": "imagerie", "pos_tag": "NOUN", "type_entity": "", "position": 564, "title": false}, {"word": "medicale", "lemma": "medicale", "pos_tag": "ADJ", "type_entity": "", "position": 565, "title": true}, {"word": ",", "lemma": ",", "pos_tag": "PUNCT", "type_entity": "", "position": 566, "title": false}, {"word": "prend", "lemma": "prendre", "pos_tag": "VERB", "type_entity": "", "position": 568, "title": false}, {"word": "radio", "lemma": "radio", "pos_tag": "NOUN", "type_entity": "", "position": 570, "title": false}, {"word": "seconde", "lemma": "seconder", "pos_tag": "ADJ", "type_entity": "", "position": 573, "title": false}, {"word": "resultat", "lemma": "resultat", "pos_tag": "NOUN", "type_entity": "", "position": 579, "title": false}, {"word": ",", "lemma": ",", "pos_tag": "PUNCT", "type_entity": "", "position": 580, "title": false}, {"word": "images", "lemma": "image", "pos_tag": "NOUN", "type_entity": "", "position": 583, "title": false}, {"word": "top", "lemma": "top", "pos_tag": "VERB", "type_entity": "", "position": 584, "title": false}, {"word": "tres", "lemma": "tres", "pos_tag": "NOUN", "type_entity": "", "position": 587, "title": false}, {"word": "grande", "lemma": "grand", "pos_tag": "ADJ", "type_entity": "", "position": 588, "title": false}, {"word": "precision", "lemma": "precision", "pos_tag": "NOUN", "type_entity": "", "position": 589, "title": false}, {"word": ">", "lemma": ">", "pos_tag": "PRON", "type_entity": "", "position": 590, "title": false}, {"word": ">", "lemma": ">", "pos_tag": "PRON", "type_entity": "", "position": 591, "title": false}, {"word": ",", "lemma": ",", "pos_tag": "PUNCT", "type_entity": "", "position": 592, "title": false}, {"word": "ajoute", "lemma": "ajouter", "pos_tag": "VERB", "type_entity": "", "position": 593, "title": false}, {"word": "specialiste", "lemma": "specialiste", "pos_tag": "NOUN", "type_entity": "", "position": 595, "title": false}, {"word": "mois", "lemma": "mois", "pos_tag": "NOUN", "type_entity": "", "position": 598, "title": false}, {"word": "necessaires", "lemma": "necessaires", "pos_tag": "ADJ", "type_entity": "", "position": 601, "title": false}, {"word": "passer", "lemma": "prendre", "pos_tag": "VERB", "type_entity": "", "position": 603, "title": false}, {"word": "crible", "lemma": "cribler", "pos_tag": "VERB", "type_entity": "", "position": 605, "title": false}, {"word": "momies", "lemma": "momie", "pos_tag": "NOUN", "type_entity": "", "position": 607, "title": true}, {"word": "cranes", "lemma": "cranes", "pos_tag": "NOUN", "type_entity": "", "position": 610, "title": false}, {"word": "centre", "lemma": "centrer", "pos_tag": "NOUN", "type_entity": "", "position": 612, "title": false}, {"word": "conservation", "lemma": "conservation", "pos_tag": "NOUN", "type_entity": "", "position": 614, "title": false}, {"word": "lyonnais", "lemma": "lyonnais", "pos_tag": "ADJ", "type_entity": "", "position": 615, "title": false}, {"word": ",", "lemma": ",", "pos_tag": "PUNCT", "type_entity": "", "position": 616, "title": false}, {"word": "grande", "lemma": "grand", "pos_tag": "ADJ", "type_entity": "", "position": 619, "title": false}, {"word": "collection", "lemma": "collection", "pos_tag": "NOUN", "type_entity": "", "position": 620, "title": false}, {"word": "45", "lemma": "45", "pos_tag": "NUM", "type_entity": "", "position": 622, "title": false}, {"word": "corps", "lemma": "corps", "pos_tag": "NOUN", "type_entity": "", "position": 623, "title": false}, {"word": "embaumes", "lemma": "embaumer", "pos_tag": "ADJ", "type_entity": "", "position": 624, "title": false}, {"word": "76", "lemma": "76", "pos_tag": "NUM", "type_entity": "", "position": 626, "title": false}, {"word": "tetes", "lemma": "tetes", "pos_tag": "NOUN", "type_entity": "", "position": 627, "title": false}, {"word": "abritee", "lemma": "abritee", "pos_tag": "VERB", "type_entity": "", "position": 629, "title": false}, {"word": "Mots", "lemma": "Mots", "pos_tag": "NOUN", "type_entity": "", "position": 631, "title": false}, {"word": "-", "lemma": "-", "pos_tag": "PUNCT", "type_entity": "", "position": 632, "title": false}, {"word": "cles", "lemma": "cles", "pos_tag": "NOUN", "type_entity": "", "position": 633, "title": false}, {"word": ":", "lemma": ":", "pos_tag": "PUNCT", "type_entity": "", "position": 634, "title": false}, {"word": "VIDEO", "lemma": "VIDEO", "pos_tag": "ADJ", "type_entity": "MISC", "position": 1, "title": false}, {"word": "Lyon", "lemma": "Lyon", "pos_tag": "ADP", "type_entity": "LOC", "position": 3, "title": false}, {"word": "Des", "lemma": "Des", "pos_tag": "DET", "type_entity": "", "position": 4, "title": true}, {"word": "momies", "lemma": "momie", "pos_tag": "NOUN", "type_entity": "", "position": 5, "title": true}, {"word": "musee", "lemma": "musee", "pos_tag": "NOUN", "type_entity": "", "position": 7, "title": true}, {"word": "Confluences_etudiees_pour_la_premiere_fois_grace", "lemma": "Confluences_etudiees_pour_la_premiere_fois_grace", "pos_tag": "NOUN", "type_entity": "MISC", "position": 9, "title": true}, {"word": "imagerie", "lemma": "imagerie", "pos_tag": "NOUN", "type_entity": "", "position": 12, "title": false}, {"word": "medicale", "lemma": "medicale", "pos_tag": "ADJ", "type_entity": "", "position": 13, "title": true}]}]